swebenchv2/__init__.py
swebenchv2/cli.py
swebenchv2/datamodule/__init__.py
swebenchv2/datamodule/github.py
swebenchv2/typings/__init__.py
swebenchv2/typings/limit.py
swebenchv2/typings/models.py
swebenchv2/typings/prs.py
swebenchv2-0.3.0.dist-info/METADATA
swebenchv2-0.3.0.dist-info/WHEEL
swebenchv2-0.3.0.dist-info/entry_points.txt
swebenchv2-0.3.0.dist-info/licenses/LICENSE
swebenchv2-0.3.0.dist-info/RECORD
