Metadata-Version: 2.4
Name: SWEBenchV2
Version: 0.3.0
Summary: Repository template for Python projects
Project-URL: Homepage, https://github.com/Mai0313/SWEBenchV2
Project-URL: Repository, https://github.com/Mai0313/SWEBenchV2
Author-email: Wei <mai@mai0313.com>
License: MIT
License-File: LICENSE
Requires-Python: >=3.10
Requires-Dist: fire>=0.7.0
Requires-Dist: httpx>=0.28.1
Requires-Dist: logfire>=4.0.0
Requires-Dist: pydantic-settings>=2.9.1
Requires-Dist: pydantic>=2.11.5
Requires-Dist: requests>=2.32.3
Requires-Dist: rich>=14.0.0
